LICENSE
README.md
setup.cfg
setup.py
volumeview/Workspace.py
volumeview/__init__.py
volumeview/create_surface_view.py
volumeview/create_vector_field_view.py
volumeview/create_volume_view.py
volumeview.egg-info/PKG-INFO
volumeview.egg-info/SOURCES.txt
volumeview.egg-info/dependency_links.txt
volumeview.egg-info/requires.txt
volumeview.egg-info/top_level.txt