Metadata-Version: 2.1
Name: volumeview
Version: 0.1.3
Summary: View 3D volumetric data using figurl
Home-page: https://github.com/magland/volumeview
Author: Jeremy Magland and Jeff Soules
Author-email: jmagland@flatironinstitute.org
License: UNKNOWN
Project-URL: Bug Tracker, https://github.com/magland/volumeview/issues
Platform: UNKNOWN
Classifier: Programming Language :: Python :: 3
Classifier: License :: OSI Approved :: Apache Software License
Classifier: Operating System :: OS Independent
License-File: LICENSE
